nyt_digits_solver/__init__.py
nyt_digits_solver/main.py
nyt_digits_solver/solver.py
nyt_digits_solver/test_solver.py
nyt_digits_solver-0.1.2.dist-info/METADATA
nyt_digits_solver-0.1.2.dist-info/WHEEL
nyt_digits_solver-0.1.2.dist-info/top_level.txt
nyt_digits_solver-0.1.2.dist-info/RECORD
