Metadata-Version: 2.4
Name: nyt-digits-solver
Version: 0.1.2
Summary: Riddle solver algorithms for the NYT Digits game
Author: Gabor Meszaros
Classifier: Programming Language :: Python :: 3
Requires-Python: >=3.11
Dynamic: author
Dynamic: classifier
Dynamic: description
Dynamic: description-content-type
Dynamic: requires-python
Dynamic: summary
